pyabk/__init__.py
pyabk/text.py
pyabk-0.1.dist-info/DESCRIPTION.rst
pyabk-0.1.dist-info/METADATA
pyabk-0.1.dist-info/RECORD
pyabk-0.1.dist-info/WHEEL
pyabk-0.1.dist-info/metadata.json
pyabk-0.1.dist-info/top_level.txt
