Metadata-Version: 2.0
Name: pyabk
Version: 0.1
Summary: First python-packaging app
Home-page: http://github.com/alibugra/pyabk
Author: alibugra
Author-email: alibugra@alibugra.com
License: MIT
Platform: UNKNOWN
